sdflmq/__init__.py
sdflmq/mqttfc_source/__init__.py
sdflmq/mqttfc_source/controller_dashboard.py
sdflmq/mqttfc_source/modules/__init__.py
sdflmq/mqttfc_source/modules/controller_core_modules.py
sdflmq/mqttfc_source/modules/controller_echo.py
sdflmq/mqttfc_source/modules/user_input.py
sdflmq/mqttfc_source/modules/core/MQTTFC_Procedures.py
sdflmq/mqttfc_source/modules/core/__init__.py
sdflmq/mqttfc_source/modules/core/broker_manager.py
sdflmq/mqttfc_source/modules/core/clients_manager.py
sdflmq/mqttfc_source/modules/core/executable_manager.py
sdflmq/mqttfc_source/modules/metadata/[template]_client_executables.json
sdflmq/mqttfc_source/modules/metadata/[template]_client_metadata.json
sdflmq/mqttfc_source/modules/metadata/__init__.py
sdflmq/mqttfc_source/modules/metadata/broker_metadata.json
sdflmq/mqttfc_source/modules/metadata/client_executables.json
sdflmq/mqttfc_source/modules/metadata/client_metadata.json
sdflmq/mqttfc_source/modules/metadata/topics_to_publish.json
sdflmq/mqttfc_source/modules/metadata/topics_to_subscribe.json
sdflmq/sdflmq_source/__init__.py
sdflmq/sdflmq_source/Core/__init__.py
sdflmq/sdflmq_source/Core/parameter_server.py
sdflmq/sdflmq_source/Core/pso_base.py
sdflmq/sdflmq_source/Core/sdflmq_client_logic.py
sdflmq/sdflmq_source/Core/sdflmq_coordinator_logic.py
sdflmq/sdflmq_source/Core/Base/__init__.py
sdflmq/sdflmq_source/Core/Base/base_io.py
sdflmq/sdflmq_source/Core/Base/converter.py
sdflmq/sdflmq_source/Core/Base/executable_class.py
sdflmq/sdflmq_source/Core/Base/topics.py
sdflmq/sdflmq_source/Core/Modules/__init__.py
sdflmq/sdflmq_source/Core/Modules/model_controller.py
sdflmq/sdflmq_source/Core/Modules/Client_Modules/__init__.py
sdflmq/sdflmq_source/Core/Modules/Client_Modules/aggregator.py
sdflmq/sdflmq_source/Core/Modules/Client_Modules/role_arbiter.py
sdflmq/sdflmq_source/Core/Modules/Coordinator_Modules/__init__.py
sdflmq/sdflmq_source/Core/Modules/Coordinator_Modules/clustering_engine.py
sdflmq-0.1.0.6.dist-info/licenses/LICENSE
sdflmq-0.1.0.6.dist-info/METADATA
sdflmq-0.1.0.6.dist-info/WHEEL
sdflmq-0.1.0.6.dist-info/entry_points.txt
sdflmq-0.1.0.6.dist-info/top_level.txt
sdflmq-0.1.0.6.dist-info/RECORD
