Metadata-Version: 2.4
Name: sdflmq
Version: 0.1.0.6
Summary: A semi-decentralized federated learning framework for Python
Home-page: https://github.com/ali-pour-amir/SDFLMQ
Author: Amir Ali-Pour
Author-email: alipouramir93@gmail.com
Classifier: Programming Language :: Python :: 3
Classifier: License :: OSI Approved :: MIT License
Classifier: Operating System :: OS Independent
Requires-Python: >=3.7
License-File: LICENSE
Requires-Dist: torch
Requires-Dist: psutil
Requires-Dist: numpy
Requires-Dist: paho-mqtt
Dynamic: author
Dynamic: author-email
Dynamic: classifier
Dynamic: description
Dynamic: description-content-type
Dynamic: home-page
Dynamic: license-file
Dynamic: requires-dist
Dynamic: requires-python
Dynamic: summary
